ft3/__init__.py
ft3/py.typed
ft3/api/__init__.py
ft3/api/cfg.py
ft3/api/enm.py
ft3/api/exc.py
ft3/api/lib.py
ft3/api/obj.py
ft3/api/typ.py
ft3/api/utl.py
ft3/api/events/__init__.py
ft3/api/events/cfg.py
ft3/api/events/enm.py
ft3/api/events/exc.py
ft3/api/events/lib.py
ft3/api/events/obj.py
ft3/api/events/utl.py
ft3/api/server/__init__.py
ft3/api/server/cfg.py
ft3/api/server/lib.py
ft3/api/server/obj.py
ft3/api/static/__init__.py
ft3/api/static/favicon.ico
ft3/api/static/swagger.html
ft3/cli/__init__.py
ft3/cli/cfg.py
ft3/cli/lib.py
ft3/cli/obj.py
ft3/cli/utl.py
ft3/core/__init__.py
ft3/core/cfg.py
ft3/core/enm.py
ft3/core/exc.py
ft3/core/lib.py
ft3/core/codecs/__init__.py
ft3/core/codecs/cfg.py
ft3/core/codecs/enm.py
ft3/core/codecs/lib.py
ft3/core/codecs/typ.py
ft3/core/codecs/utl.py
ft3/core/strings/__init__.py
ft3/core/strings/cfg.py
ft3/core/strings/enm.py
ft3/core/strings/exc.py
ft3/core/strings/lib.py
ft3/core/strings/obj.py
ft3/core/strings/typ.py
ft3/core/strings/utl.py
ft3/core/typ/__init__.py
ft3/core/typ/cfg.py
ft3/core/typ/lib.py
ft3/core/typ/obj.py
ft3/core/typ/typ.py
ft3/core/typ/utl/__init__.py
ft3/core/typ/utl/check.py
ft3/core/typ/utl/hint.py
ft3/docs/__init__.py
ft3/docs/cfg.py
ft3/docs/enm.py
ft3/docs/lib.py
ft3/docs/obj.py
ft3/docs/utl.py
ft3/docs/static/__init__.py
ft3/docs/static/conf.tpl
ft3/docs/static/favicon.ico
ft3/docs/static/logo.png
ft3/loggers/__init__.py
ft3/loggers/cfg.py
ft3/loggers/exc.py
ft3/loggers/lib.py
ft3/loggers/obj.py
ft3/loggers/typ.py
ft3/loggers/utl.py
ft3/objects/__init__.py
ft3/objects/cfg.py
ft3/objects/enm.py
ft3/objects/exc.py
ft3/objects/lib.py
ft3/objects/typ.py
ft3/objects/utl.py
ft3/objects/fields/__init__.py
ft3/objects/fields/obj.py
ft3/objects/metas/__init__.py
ft3/objects/metas/obj.py
ft3/objects/metas/utl.py
ft3/objects/objs/__init__.py
ft3/objects/objs/obj.py
ft3/objects/queries/__init__.py
ft3/objects/queries/obj.py
ft3/template/__init__.py
ft3/template/api/__init__.py
ft3/template/api/pets.py
ft3-1.1.0.dist-info/licenses/LICENSE
ft3-1.1.0.dist-info/METADATA
ft3-1.1.0.dist-info/WHEEL
ft3-1.1.0.dist-info/entry_points.txt
ft3-1.1.0.dist-info/top_level.txt
ft3-1.1.0.dist-info/RECORD
