Metadata-Version: 2.4
Name: ft3
Version: 1.1.0
Summary: Zero-dependency Python framework for object oriented development.
Author-email: Dan <dan@1howardcapital.com>
Maintainer-email: Dan <dan@1howardcapital.com>
Project-URL: Documentation, https://ft3.readthedocs.io/en/stable/ft3.html
Project-URL: Homepage, https://ft3.readthedocs.io/en/stable/
Project-URL: Repository, https://github.com/dan1hc/ft3.git
Project-URL: Issues, https://github.com/dan1hc/ft3/issues
Project-URL: Changelog, https://github.com/dan1hc/ft3/blob/main/CHANGELOG.md
Keywords: dataclasses,ft3,framework,openapi,rest,swagger
Classifier: Development Status :: 3 - Alpha
Classifier: License :: OSI Approved :: GNU Library or Lesser General Public License (LGPL)
Classifier: Operating System :: OS Independent
Classifier: Programming Language :: Python :: 3.11
Classifier: Programming Language :: Python :: 3.12
Classifier: Programming Language :: Python :: 3.13
Classifier: Topic :: Software Development :: Libraries :: Application Frameworks
Classifier: Typing :: Typed
Requires-Python: >=3.10
License-File: LICENSE
Requires-Dist: typing_extensions; python_version < "3.11"
Provides-Extra: develop
Requires-Dist: mypy==1.11.*; extra == "develop"
Requires-Dist: pre-commit<3.9,>=3.7; extra == "develop"
Requires-Dist: coverage==7.6.*; extra == "develop"
Requires-Dist: pytest==8.3.*; extra == "develop"
Requires-Dist: pytest-cov==5.0.*; extra == "develop"
Requires-Dist: ruff==0.5.*; extra == "develop"
Requires-Dist: commonmark==0.9.*; extra == "develop"
Requires-Dist: sphinx<9,>=7; extra == "develop"
Provides-Extra: docs
Requires-Dist: commonmark==0.9.*; extra == "docs"
Requires-Dist: sphinx<9,>=7; extra == "docs"
Dynamic: license-file
